myImport/__init__.py
myImport/valueInfo.py
myImport-0.0.1.dist-info/METADATA
myImport-0.0.1.dist-info/WHEEL
myImport-0.0.1.dist-info/top_level.txt
myImport-0.0.1.dist-info/RECORD
