Metadata-Version: 2.1
Name: myImport
Version: 0.0.1
Summary: UNKNOWN
Home-page: https://gitee.com/qq1418381215/myImport
Author: Liu Yancheng
Author-email: 1418381215@qq.com
License: UNKNOWN
Keywords: value
Platform: UNKNOWN
Requires-Dist: numpy
